Workbook

Sheet 1. Executive Summary
A1: THE RELIEF PROS, LLC — BOOKKEEPING SERVICES
A2: Texas LLC, 100% women-owned · Dallas-Fort Worth · Business plan prepared July 2026 · "Relief from the back office"
A4: The Business
A5: The Relief Pros, LLC provides fixed-fee monthly bookkeeping and books-cleanup services to Dallas-Fort Worth small businesses, delivered remotely on QuickBooks Online. The practice is owned and controlled by Sarah Bowen, MBA (100% owner; all service delivery, accounting judgment, and client relationships). Her husband Brad, a disabled veteran and experienced software builder, provides technical and administrative support under her direction: the website, SEO and Google Business Profile, the client document portal, receipt pipelines, invoicing, and ACH autodraft payment collection. Every client is on autodraft from day one, so the firm carries zero accounts receivable by design. The firm sells continuity and judgment: one named professional who answers, in a market whose low-price tier has repeatedly collapsed (Bench, Dec 2024; Botkeeper, Feb 2026) and whose largest vendor (Intuit) is retiring its competing QuickBooks Live service effective July 29, 2026, publicly refocusing on supporting independent bookkeepers.
A7: The Opportunity in Five Numbers
A8: Number | B8: Value | D8: What it means
A9: DFW small businesses | B9: 988,987 | D9: #5 US metro; no dominant local brand (top firm: 74 Google reviews)
A10: National price umbrella | B10: $300-$700/mo | D10: Set by QuickBooks Live, Xendoo, Bookkeeper360; independents price at or above it
A11: Bookkeeper supply | B11: -6% by 2034 | D11: BLS projection; ~170,000 annual openings, all from replacement need, none from growth
A12: Client lifetime (12% churn) | B12: ~8 years | D12: Monthly bookkeeping is the stickiest recurring service asset class
A13: Startup cash required | B13: Under $700 | D13: Entity, EIN, and bank account already exist; certification is free; insurance is the main cost
A15: Financial Snapshot (Moderate Case)
A16: Milestone | B16: Clients | C16: Recurring revenue | D16: Cleanup revenue | E16: Total revenue | F16: Timing
A17: Operating break-even | B17: 1 | C17: First retainer covers all fixed costs | D17: n/a | E17: Profitable from client #1 | F17: Month 1-2
A18: Exit Year 1 | B18: 9 | C18: $48,600/yr run-rate ($450 avg) | D18: $15,000-$30,000 | E18: $40,000-$60,000 collected | F18: Month 12
A19: Solo delivery ceiling | B19: 15 | C19: $117,000/yr ($650 avg, matured book) | D19: +cleanup | E19: ~$130,000-$140,000 | F19: Year 2-3
A20: With payroll ladder + leverage | B20: 20-26 | C20: $160,000-$200,000+ | D20: +cleanup | E20: Scaling decision | F20: Year 3+
A21: Two honest structural facts this plan is built around. First: early pricing lands at $350-$450 per client, not the $500-$650 the mature book earns — blended $650 is a month-12+ outcome that arrives with testimonials and niche proof, and the model (Tab 7) prices the ramp, not the destination. Second: a solo bookkeeper's delivery ceiling is roughly $117,000 of annual recurring revenue regardless of pricing tier. It is set by hours, not by price: ~110 working hours per month, less roughly 30% that any owner-operator spends selling, learning, and administering, leaves ~77 deliverable hours — about 15 mature clients at 5 hours each, and only about 8 while every client is still new. Price changes how many clients are needed to reach the ceiling, not the ceiling. Growth beyond it comes from three costed levers: the service ladder (payroll administration, sales tax, controller-level review), delegated preparation labor under Sarah's review, and niche specialization (niche-focused firms earn 51% higher revenue per client, AICPA CAS Benchmark).
A23: Why Now
A24: Labor shortage | B24: Accounting graduates down 6.6% YoY; CPA firms shedding small clients and referring bookkeeping out (AICPA 2025 Trends).
A25: Incumbent retreat | B25: Intuit is retiring QuickBooks Live effective July 29, 2026 — two days after this plan was written, so this is an announced change taking effect, not a completed one. Intuit stated the service damaged relationships with its accountant channel. Intuit also cut 17% of its workforce (SEC 8-K, May 20, 2026) while pivoting to AI. Verify the retirement completed as announced before relying on it in a sales conversation.
A26: Tech-first failures | B26: Bench: $100M+ raised, bankruptcy with $65.4M liabilities. Botkeeper: ~$90M raised, shut Feb 2026. Cheap-at-scale human bookkeeping is demonstrated to be structurally unprofitable.
A27: AI as tailwind | B27: Current AI drafts categorization for human review; it compresses hours per client, which raises a small firm's capacity. Stanford GSB research: AI-using accountants close 7.5 days faster and serve more clients; the judgment and communication work clients pay for remains human.
A28: Household timing | B28: Sarah's MBA completes within months; the LLC, bank account, and technical infrastructure already exist; certification is free and takes weeks.
A30: The Ask of This Document
A31: This plan is presented for stress-testing, not applause. Every figure is cited (Tab 14); every assumption in the financial model (Tab 7) is an editable input; the known weaknesses are stated in Tab 10 and the hardest anticipated questions are pre-answered in Tab 13, including the ones that argue against proceeding. Decision requested: proceed / modify / decline, with Sarah's certification start date as the first milestone if proceeding, and the 90-day validation sprint (Tab 5) as the first kill-or-continue gate.
A33: Source: All figures cross-referenced in Tab 14 (Sources). Key: SBA 2025 metro profiles; AICPA 2025 MAP Survey & 2024 CAS Benchmark (n=206); Ignition 2025/26 Pricing Benchmark (n=219); BLS OEWS May 2025 (pulled via API) & Employment Projections 2024-34; Intuit SEC 8-K 5/20/2026; six DFW firm pricing pages.

Sheet 2. Company & Organization
A1: COMPANY & ORGANIZATION
A2: Legal structure, ownership, roles, and governance
A4: Legal Structure (existing — verified with owners July 2026)
A5: Item | B5: Status | C5: Detail | D5: Action needed
A6: Entity | B6: COMPLETE | C6: The Relief Pros, LLC — Texas limited liability company. The entity is dedicated: no other ventures operate under it, so no cross-liability with unrelated activities. | D6: None
A7: Operating name | B7: DECIDED | C7: The firm operates under the LLC's legal name directly — no DBA. "The Relief Pros" contains no restricted terms; Texas law prohibits non-CPAs from using "accountant" or "accounting services" in public offers (TSBPA enforcement guidance), so all marketing uses "bookkeeping." Google Business Profile category: "Bookkeeping service." A DBA (Form 503, $25) remains available later if marketing ever demands a more descriptive name. | D7: None now
A8: Ownership & control | B8: COMPLETE | C8: Sarah Bowen is the 100% owner. SBA WOSB rules (13 CFR 127) determine ownership without regard to community property law, so 100% ownership in a community-property state is clean. Control: Sarah is the highest officer and controls day-to-day operations and long-term decisions — the operating agreement should say so explicitly (one-hour attorney review). | D8: One-hour operating-agreement language check before WOSB filing
A9: EIN / bank | B9: COMPLETE | C9: EIN issued; business checking open. | D9: None
A10: Annual compliance | B10: CURRENT | C10: Franchise tax / Public Information Report filed annually by the family's CPA; filings are current. ($0 tax below the no-tax-due threshold, but the filing itself is mandatory.) | D10: Continue CPA engagement
A11: Insurance | B11: BEFORE CLIENT #1 | C11: E&O professional liability $1M/$1M (~$37-50/mo) naming the LLC and covering both individuals performing services; claims-made policy, so the retroactive date must precede the first engagement. Cyber liability (~$47/mo) before holding client credentials. | D11: Bind E&O at launch; declare full service scope on application
A13: Roles & Division of Labor
A14: Role architecture note: Sarah owns and controls the firm — every description below is written the way SBA examiners will read it for the WOSB control test. Brad provides technical and administrative services under her direction. He makes no accounting judgments; anything ambiguous goes to Sarah's review queue. He also never holds payment authority over any client's payroll or tax accounts (see the Trust Fund Recovery Penalty guardrail, Tab 6).
A15: Role | B15: Who | C15: Responsibilities | D15: Boundary
A16: Principal — owns and controls the firm | B16: Sarah Bowen, MBA | C16: All accounting judgment: chart of accounts design, reconciliation problem-solving, journal entries, month-end close, financial statement review, client advisory conversations. Signs engagement letters, sets pricing, hires, and makes every strategic decision. Final review of all work product. | D16: Sole authority on accounting judgments and firm decisions
A17: Web presence & lead generation (under Sarah's direction) | B17: Brad Bowen | C17: Builds and runs the website; SEO; Google Business Profile setup and map-pack optimization; directory profiles (Find-a-ProAdvisor, Clutch, local citations); review-request system; lead lists from new-business filings; outreach sequences Sarah approves. | D17: Marketing infrastructure only; Sarah approves all client-facing positioning
A18: Client operations & document pipeline (under Sarah's direction) | B18: Brad Bowen | C18: Builds and runs the client document upload portal and Dropbox file system; receipt collection and chasing; onboarding logistics (checklists, access requests, W-9 collection at signup); bank-feed rule setup per Sarah's specifications; software administration; scheduling; records archive. | D18: No categorization judgments; flags-and-queues model — ambiguity goes to Sarah
A19: Billing & payment collection (under Sarah's direction) | B19: Brad Bowen | C19: Administers ACH autodraft enrollment at engagement signing; runs the monthly draft on the 1st; sends receipts and statements to clients; handles failed-payment retry and service-pause per firm policy; tracks cleanup-project deposits. The autodraft system means no one ever chases an invoice. | D19: Collects on Sarah's signed engagements only; never touches client tax/payroll funds
A20: Future hire #1 (Year 2-3) | B20: Contract preparer | C20: Transaction categorization and reconciliation prep under Sarah's review, added when client count exceeds ~12-14 (the solo capacity inflection). | D20: Work-paper preparer only; Sarah reviews and closes
A22: Why This Team
A23: Sarah: honors MBA (finance and analysis training that maps to the review-and-advisory ladder where margins are highest), organized and detail-oriented, credible to the exact audience that distrusts anonymous providers. Brad: shipped production software solo (a full accuracy-gated web application in ~6 working days); brings automation and web-marketing capability most solo bookkeeping practices lack, which industry benchmarks say is the difference between carrying 14 and 24 clients at the same quality. The pairing covers the two failure modes of new practices: technical operations without judgment, and judgment without operations. The honest accounting of capacity: this is 1.0 production FTE (Sarah), not 1.5 — Brad's hours build systems and pipeline, they do not close books. All capacity math in this plan is computed on 1.0 production FTE.
A25: Certification & Credential Timeline (Sarah)
A26: Step | B26: When | C26: Cost | D26: Note
A27: Skills runway: AccountingCoach fundamentals + QBOA practice file | B27: Weeks 1-6 (parallel) | C27: $0 | D27: Free QuickBooks Online Accountant signup includes a persistent full-featured "Your Books" file — a real practice sandbox. Drill the close checklist; deliberately wreck and clean a practice file before touching client books.
A28: QuickBooks Online Level 1 Certification (ProAdvisor) | B28: Weeks 1-3 | C28: $0 | D28: Via coursework, not test-out: embedded exams have unlimited attempts and earn CPE. Publishes Find-a-ProAdvisor directory profile immediately. Independent audit of 223 live job postings: ProAdvisor is the only bookkeeping credential employers or clients ever name.
A29: Xero Advisor Level 1 | B29: Week 3 (~2 hours) | C29: $0 | D29: Cheap hedge against Intuit platform risk; US market is ~40-50:1 QuickBooks by revenue, so stop at Level 1. Note: Xero certification expires every 12 months.
A30: E&O + cyber insurance bound | B30: Before client #1 | C30: ~$1,000-1,400/yr | D30: Claims-made retroactive-date logic makes early binding permanent protection.
A31: QuickBooks Online Level 2 | B31: Day ~90+ | C31: $0 | D31: 200 ProAdvisor points (largest single non-client point source). Intuit recommends the 90-day gap.
A32: WOSB certification (federal) | B32: Months 2-4 | C32: $0 | D32: Free via MySBA, ~90 days. See Tab 11 — including the honest finding that Texas ended its women/minority HUB program in Dec 2025, and what WOSB does and does not deliver in this NAICS code.
A33: AIPB Certified Bookkeeper | B33: Year 2-3, only if a prospect segment demands it | C33: ~$314 (workbooks) to $1,495 (full course) | D33: Requires 2 years / 3,000 hours of experience — a maturity credential. Market-value audit found zero employer or client demand for it (0 mentions in 223 postings); buy the workbooks as training material, defer the exam decision.
A34: ANNUAL: ProAdvisor recertification | B34: Every June (hard deadline June 30) | C34: $0 | D34: Missing it as Level 2 revokes both levels, unpublishes the directory profile, and forfeits 300 points. Permanent June 1 calendar entry.
A35: Dec 2026: platform migration check | B35: December 2026 | C35: $0 | D35: QBOA is discontinued Dec 31, 2026. Confirm the firm is on Intuit Accountant Suite CORE (free), not the Accelerate beta that begins billing $149/mo on Jan 20, 2027.
A37: Source: TSBPA enforcement FAQ (title restrictions); 13 CFR 127 (WOSB ownership/control); Texas Comptroller franchise tax/PIR; Intuit ProAdvisor FAQ (updated 7/14/2026); LinkedIn postings audit n=223 (original data, July 2026); Insureon bookkeeper premium medians; Xero FY26 Annual Report. Full citations Tab 14.

Sheet 3. Market Analysis
A1: MARKET ANALYSIS
A2: Market size, competition, target client, and the honest saturation question
A4: Market Size & Structure (Dallas-Fort Worth)
A5: Measure | B5: Value | C5: Implication | D5: Source grade
A6: DFW small businesses | B6: 988,987 | C6: #5 US metro by small-business count. Even a 0.0015% share (15 clients) fills the solo capacity ceiling — the plan does not require meaningful market share. | D6: Verified (SBA 2025 metro profile)
A7: New TX business filings, DFW share | B7: ~11,000-13,000/month | C7: Top-of-funnel only: new businesses are broke and die fast (48.6% gone in 5 years). Used as a drip list that matures — a filing from 12 months ago is a business with revenue, a shoebox of receipts, and its first tax-season panic. | D7: Verified count; honest reframe applied
A8: Employed bookkeepers, DFW | B8: 34,930 (median wage $51,720) | C8: Deep incumbent labor pool, but almost all W-2 employees — the competitive set for a firm is far smaller. | D8: Verified (BLS OEWS May 2025, via API)
A9: Bookkeeping occupation trend | B9: -6% by 2034; ~170,000 openings/yr, 100% from replacement | C9: The occupation shrinks while replacement demand stays high: retiring solo practitioners are literally the acquisition pipeline (Tab 11 expansion section). | D9: Verified (BLS Employment Projections 2024-34)
A10: National price umbrella | B10: $300-$700/mo | C10: Set by QuickBooks Live (retiring July 29, 2026), Xendoo, Bookkeeper360. Independents price at or above it. The firm never needs to price under $300 to win. | D10: Verified (published pricing pages)
A12: The Competitive Collapse at the Low End (why the umbrella holds)
A13: Competitor | B13: What happened | C13: What it proves | D13: Date
A14: Bench Accounting | B14: $100M+ raised; abrupt shutdown/bankruptcy, $65.4M liabilities; thousands of clients stranded mid-year | C14: Venture-scaled cheap human bookkeeping is structurally unprofitable; stranded clients now distrust anonymous providers | D14: Dec 2024
A15: Botkeeper | B15: ~$90M raised; shut down | C15: The "AI bookkeeper" at scale did not survive contact with real books | D15: Feb 2026
A16: QuickBooks Live | B16: Intuit is retiring its own $300/mo competing service, citing damage to its accountant channel. ANNOUNCED, effective July 29, 2026 — two days after this plan was written. Treat as in progress, not completed, until confirmed. | C16: The largest vendor chose the independent-bookkeeper channel over competing with it | D16: Effective 7/29/2026
A17: Intuit (company-wide) | B17: 17% workforce reduction while pivoting to an "AI-native platform" (SEC 8-K) | C17: Platform risk is real: Intuit is simultaneously the firm's channel and a potential future competitor — hence the Xero hedge and pass-through billing design | D17: May 2026
A19: Local Competition & the Saturation Question (answered honestly)
A20: Barriers to entry are low — no license is required in Texas, and anyone can call themselves a bookkeeper. So the market is crowded at the commodity layer and thin at the trust layer: the most-reviewed dedicated bookkeeping firm found in DFW has 74 Google reviews, which means no local brand owns the metro. Fragmentation is the norm; word-of-mouth and referral relationships allocate most clients (57% of accounting clients come from referrals vs ~3% from ads). The plan's answer to saturation is not to out-advertise the crowd but to (1) specialize in two niches where books are genuinely hard, (2) look more established than the crowd (professional site, map pack, reviews, portal — Brad's build list), and (3) win the referral layer through CPA relationships. What this plan does NOT claim: that showing up is enough. The 90-day validation sprint (Tab 5) exists precisely because acquisition, not delivery, is the unproven step.
A22: Target Client Profile & Niches
A23: Segment | B23: Why chosen | C23: Risk & mitigation | D23: Roster rule
A24: Home-services contractors (primary) | B24: High pain (job costing, progress billing, 1099 subs), high willingness to outsource, low competition for specialization, high ticket sizes | C24: Housing-cycle sensitivity; mitigated by monthly-retainer stickiness and diversified trades | D24: Target 40-50% of roster
A25: Professional services (secondary) | B25: Clean books, low transaction volume, stable, high retention — the capacity-friendly ballast of the roster | C25: Lower fees per client; acceptable because hours are also lower | D25: Target 25-35%
A26: Restaurants (opportunistic only) | B26: Acute pain (POS reconciliation, tips, vendors) and underserved | C26: ~49% close within 5 years — client mortality is churn no service quality prevents | D26: CAPPED at ~25% of roster
A27: Screening rules (all segments) | B27: Business 2+ years old preferred; declines: brand-new businesses (price-sensitive, high mortality), clients refusing ACH autodraft, clients refusing the document portal | C27: Bad-fit clients are the top capacity killer in practitioner literature | D27: Scorecard applied before every proposal
A29: AI: Threat Assessment (the question every reviewer will ask)
A30: The best long-run evidence is Autor & Thompson (NBER w33941, 2025): from 1980-2018, automation cut bookkeeping employment by one-third while raising real wages nearly 40% — automation strips the easy tasks, and what remains requires more expertise and pays better. Stanford GSB task-level research (277 accountants, 79 firms, 2025) finds AI automates categorization, data entry, and reconciliation prep while judgment, quality assurance, communication, and advisory survive — AI users close 7.5 days faster and serve more clients. This plan is built for that world: Brad automates the shrinking layer inside the firm (bank rules, pipelines, portal) so Sarah's hours concentrate in the surviving layer (review, close, advisory). AI is margin expansion for a two-person firm and margin destruction for bodies-in-seats firms. The residual risk — a "done-for-you" Intuit AI product good enough to skip bookkeepers entirely — is monitored in the risk register (Tab 10) with a named tripwire.
A32: Source: SBA 2025 metro profiles; BLS OEWS May 2025 + Employment Projections 2024-34 (API pulls); NBER w33941 (Autor & Thompson); Stanford GSB (Choi & Xie, June 2025); Intuit SEC 8-K 5/20/2026; LendingTree failure-rate analysis of BLS data; Owner.com restaurant closure data; published pricing pages of six DFW firms + three national providers. Full citations Tab 14.

Sheet 4. Services & Pricing
A1: SERVICES & PRICING
A2: What the firm sells, what it refuses to sell, and how money is collected
A4: Service Menu
A5: Service | B5: Price | C5: What is included | D5: Notes
A6: Monthly bookkeeping — Starter | B6: $350/mo | C6: Up to 2 accounts, ~100 transactions: categorization, bank/credit-card reconciliation, monthly P&L + balance sheet, closing-date lock | D6: Entry tier; where most first-ten clients land
A7: Monthly bookkeeping — Standard | B7: $450-$550/mo | C7: Up to 4 accounts, ~250 transactions: everything in Starter + loan tie-outs, A/R-A/P aging review, monthly summary note in plain English | D7: Core tier at maturity
A8: Monthly bookkeeping — Complex | B8: $650-$950/mo | C8: Contractors/restaurants: job costing or POS reconciliation, class tracking, subcontractor 1099 tracking, monthly review call | D8: Niche tier; where the 51% niche premium lives
A9: Diagnostic review | B9: $300-$500 flat, paid upfront | C9: Read-only review of an existing file: reconciliation status, Opening Balance Equity check, Undeposited Funds check, uncategorized backlog count, written findings | D9: Credited 100% against cleanup if engaged; converts tire-kickers into evidence
A10: Cleanup / catch-up projects | B10: 2-2.5x monthly rate per month of mess | C10: 12-step cleanup order (audit COA first, then vendors, feeds, categorize, reconcile oldest-to-newest, tie to filed returns, lock) | D10: 50% deposit before work, balance on delivery; benchmark: a 12-month cleanup runs 40-60 hours
A11: Year-end 1099 preparation | B11: Per-form January fee | C11: 1099-NEC/MISC prep and filing; W-9s collected at client onboarding, not in January | D11: Counter-seasonal revenue; Jan 31 IRS deadline
A13: Deliberately Excluded Services (and why)
A14: Excluded | B14: Reason | C14: What we do instead | D14: Revisit when
A15: Tax preparation | B15: Out of scope by owner decision; different liability profile and seasonal crush | C15: Refer to partner CPAs — which is also the referral flywheel: CPAs reciprocate with bookkeeping referrals | D15: Not planned
A16: Payroll administration | B16: Two independent tripwires: (1) IRS Trust Fund Recovery Penalty makes anyone with payment authority PERSONALLY liable for unpaid withholding; (2) Texas taxes payroll processing as data processing (6.25%+ on 80% of the charge) | C16: Client runs Gusto/ADP; firm books the entries correctly (the payroll journal-entry skill stays in-house) | D16: Year 2+, priced with sales tax collected, never with payment authority
A17: A/P & A/R management | B17: Same Texas data-processing tax exposure; also the highest scope-creep service | C17: Books-only engagements; aging reviewed, never worked | D17: Year 2+ decision
A18: Website maintenance services | B18: Out of scope by owner decision | C18: Brad builds the firm's own web presence only | D18: Not planned
A19: CFO/controller advisory | B19: Premature until the book matures; sold before capability = reputation risk | C19: Monthly summary notes plant the seed; formalize later at $2,000+/mo tier | D19: Year 3+ (the natural MBA endgame)
A21: Texas Sales Tax Treatment (verified against Comptroller guidance)
A22: Service | B22: Taxable? | C22: Basis | D22: Plan handling
A23: Bookkeeping, reconciliation, financial statements | B23: NO | C23: Professional service, not enumerated as taxable | D23: Core offering — clean
A24: Payroll processing, A/P, A/R services | B24: YES | C24: Taxable "data processing" (6.25%+ local, on 80% of charge); Comptroller updated the data-processing rule in 2025 | D24: Excluded at launch (see above)
A25: Mixed contracts | B25: Depends | C25: 5% incidental rule: a taxable component over 5% of the contract can taint the invoice | D25: Services invoiced as separate line items, always
A26: Monitored item | B26: — | C26: Heavily automated bookkeeping arguably drifts toward the taxable data-processing category as automation deepens | D26: Annual check with the CPA; flagged in risk register
A28: How Money Is Collected: ACH Autodraft Policy (zero accounts receivable by design)
A29: Payment terms are not negotiated per-client; they are the firm's standing policy, administered by Brad. At engagement signing, every client signs (1) the engagement letter and (2) an ACH debit authorization. Retainers draft automatically on the 1st of each month, in advance. Failed drafts retry on day 3; unresolved by day 10, service pauses automatically and the client is notified — work never continues on credit. Cleanup projects: 50% deposit drafts at signing, balance drafts on delivery. Receipts are emailed automatically after every draft. The result: the firm carries zero accounts receivable, no one ever makes a collections call, and revenue is known on the 1st of every month.
A30: Payment rail | B30: Cost | C30: Fit | D30: Verdict
A31: QuickBooks Payments (ACH inside QBO) | B31: ~1% per ACH transaction (≈$4.50 on a $450 draft); rates confirmed at enrollment | C31: Native to the stack; recurring sales receipts auto-draft and auto-reconcile; ProAdvisor accounts get preferred processing rates | D31: RECOMMENDED at launch
A32: Melio | B32: Free standard ACH | C32: Free, but weaker recurring-authorization workflow; adds a vendor to the stack | D32: Backup / fee-sensitive fallback
A33: Ignition | B33: From ~$39-99/mo platform fee + processing | C33: Proposals + engagement letters + auto-payment in one flow; the industry standard at scale | D33: Adopt at ~10+ clients when proposal volume justifies it
A34: Relay (business banking) | B34: Free ACH transfers | C34: Good operating bank; ACH collection requires more manual setup | D34: Bank choice, not the collection rail
A36: Pricing Honesty: the Ramp
A37: Red-team finding adopted into the model: the first ten clients will close at $350-$450, not $500-$650, because a firm without testimonials anchors low. Blended $650 is a month-12+ outcome earned through niche proof (job-costing and POS demo workflows are built BEFORE the first sales conversation), reviews, and annual price steps written into the engagement letter (fees adjust each January with 30 days' notice). Tab 7 models the ramp explicitly; no revenue line in this plan assumes mature pricing on day one.
A39: Source: Texas Comptroller Pub. 94-127 + 2025 data-processing rule update (Grant Thornton alert); IRS TFRP guidance; Intuit QuickBooks Payments published rates; Ignition/Melio published pricing; Ignition 2025/26 Pricing Benchmark (n=219); Jetpack Workflow hours-per-client benchmarks; practitioner cleanup benchmarks (Winnie Jayne 12-step, 200+ files). Full citations Tab 14.

Sheet 5. Marketing & Sales
A1: MARKETING & SALES
A2: Channels ranked by evidence, customer economics, and the 90-day validation sprint
A4: Acquisition Channels, Ranked (57% of accounting clients come from referrals; ~3% from ads)
A5: Channel | B5: Est. CAC | C5: How it works here | D5: Rank & rationale
A6: Warm network + first clients | B6: ~$0 | C6: First 2-3 sets of books at reduced fee for known businesses — priced as training, reviewed by a CPA, harvested for testimonials | D6: #1 — cheapest proof; every practitioner path starts here
A7: CPA referral partnerships | B7: ~$0-100 (lunches) | C7: The structural advantage: this firm sells NO tax prep, so CPAs shedding bookkeeping work refer without competitive fear, and receive clean year-end files back. Approach window: May-June, right after tax season pain peaks. Target: 5 standing relationships. | D7: #2 — the compounding channel; referrals close at high rates and price higher
A8: Google Business Profile + local SEO (Brad) | B8: Time only | C8: Map-pack presence, review engine (request after each clean close), service pages per niche and suburb. Brad has shipped this stack before. | D8: #3 — slow to rank (months), then durable and free
A9: Find-a-ProAdvisor directory | B9: $0 | C9: Free listing publishes with Level 1 certification. Practitioner reports on lead volume are genuinely mixed (some get 6-7 leads, some zero). | D9: #4 — treat as upside, never as the plan
A10: New-filing drip list (Brad) | B10: Time + ~$20/mo tooling | C10: Scrape monthly DFW filings; drip sequence timed to month 10-14 after formation, when the shoebox and first tax panic arrive. Expected conversion under 1%. | D10: #5 — cheap automatable experiment; matures in year 2
A11: Paid ads | B11: $300-1,500/client (industry) | C11: Only ~3% of accounting clients arrive via ads; commodity keywords are bid up by national providers | D11: DEPRIORITIZED — revisit only with a proven landing funnel
A13: Customer Economics (honest-retention version)
A14: Measure | B14: Value | C14: Basis | D14: Note
A15: Average revenue per client | B15: $400-450/mo early → $650 matured | C15: Pricing ramp, Tab 4 | D15: Blended across tiers
A16: Retention assumption, years 1-2 | B16: 75-85% annual | C16: Small accounting firms typically retain 60-70%; well-run firms 90-96%. New firms do not earn the top band immediately. | D16: 95% is a year-3+ goal, not an assumption
A17: Client lifetime at 80% retention | B17: ~4.5 years average | C17: Geometric mean of the honest band | D17: Doubles if retention reaches 90%+
A18: Lifetime value (LTV) | B18: $15,000-$20,000 | C18: $450-650/mo × honest lifetime, net of the ramp | D18: The $30k+ LTV seen in industry content assumes established-firm retention — rejected
A19: CAC, blended | B19: Under $150 | C19: Referral-dominant channel mix above | D19: LTV:CAC exceeds 100:1 — acquisition is constrained by time and trust, not money
A20: Payback period | B20: First month's draft | C20: Autodraft on the 1st, in advance | D20: No financing gap exists in this model
A22: Sales Process (Sarah closes; Brad fills the calendar)
A23: Stage | B23: Owner | C23: What happens | D23: Conversion tool
A24: Lead → discovery call | B24: Brad routes, Sarah takes the call | C24: 20-minute call: business age, entity type, account count, state of the books, screening scorecard applied | D24: Calendar link on site; scorecard declines bad fits politely
A25: Discovery → diagnostic | B25: Sarah | C25: Paid diagnostic ($300-500, upfront) on the existing file — converts "how much?" into evidence, filters non-serious prospects, and is credited against cleanup | D25: The diagnostic IS the sales demo
A26: Diagnostic → proposal | B26: Sarah | C26: Written findings + fixed-fee proposal: cleanup quote + monthly tier. Niche demo workflows (job-costing, POS reconciliation) shown here. | D26: Fixed fees remove hourly-anxiety objections
A27: Proposal → engagement | B27: Sarah signs; Brad onboards | C27: Engagement letter + ACH authorization signed in one sitting; deposit drafts immediately; onboarding checklist starts | D27: No engagement without autodraft — standing policy
A29: The 90-Day Validation Sprint (kill criteria, set before feelings are involved)
A30: The single least-validated assumption in this plan is not delivery — it is whether Sarah wants to do, and converts at, relationship sales. Rather than argue about it, the plan tests it cheaply: within 90 days of certification, complete 30 outreach conversations (CPA lunches, trade associations, warm network), issue 10 proposals, and sign 3 clients. Hit it: proceed to the Year-1 plan. Miss it badly: the fallback is subcontract/white-label production for established firms (almost no selling, lower margin, $30-50/hr domestic benchmark) while the decision gates in Tab 12 govern next steps. Either way, the household learns the truth for under $700.
A32: Source: Referral/ads channel mix: industry surveys cited in Tab 14; CPA capacity shortage: AICPA 2025 Trends (graduates -6.6% YoY); retention benchmarks: SmartFirm & Agiled compilations; white-label rates: Remote Books Online & Maxim Liberty published pricing; ProAdvisor directory lead reports: practitioner threads (anecdotal, labeled). Full citations Tab 14.

Sheet 6. Operations
A1: OPERATIONS
A2: The monthly machine: document pipeline, close workflow, software stack, and guardrails
A4: Monthly Cadence (per client)
A5: Days | B5: Step | C5: Detail | D5: Owner
A6: 1st | B6: Revenue day | C6: ACH autodraft runs for every client; receipts auto-emailed; failed drafts flagged for day-3 retry | D6: Brad (system)
A7: 1st-5th | B7: Document intake | C7: Portal auto-requests statements/receipts; automated reminders day 1, 3, 5; Brad personally chases stragglers — Sarah never chases documents | D7: Brad
A8: 5th-10th | B8: Preparation | C8: Bank feeds categorized against Sarah's rules; exceptions queued for her review; reconciliations prepped | D8: Brad preps mechanics, Sarah judges
A9: 10th-15th | B9: Close | C9: Sarah: verify beginning balances FIRST, reconcile every account, adjusting entries, balance-sheet review line-by-line (every line provable to an external document), trial-balance variance scan vs prior period | D9: Sarah
A10: 15th | B10: Deliver & lock | C10: P&L + balance sheet + plain-English summary note delivered via portal; closing date set with password | D10: Sarah delivers, Brad archives
A11: Client didn't send docs? | B11: Standing policy | C11: Close proceeds on time; missing items parked in a clearly-labeled holding account and listed in the summary note. Engagement letter states this. Chronic offenders hit the scorecard at renewal. | D11: Policy, not negotiation
A13: Non-Negotiable Guardrails (the firm's own checks and balances)
A14: Guardrail | B14: Rule | C14: Why | D14: Enforced by
A15: Trust Fund Recovery Penalty | B15: No one at the firm EVER holds payment authority over a client's payroll or tax accounts | C15: IRS holds "responsible persons" personally liable for unpaid withholding — unlimited, non-dischargeable exposure | D15: Engagement letter clause + service exclusions (Tab 4)
A16: No force-balancing | B16: A reconciliation difference is never plugged to an expense or "adjustment" — it is diagnosed (beginning balance, discrepancy report, audit log) or escalated | C16: Plugs bury errors permanently and are the cardinal sin of the trade | D16: Close checklist; Sarah's sole domain
A17: Period locking | B17: Closing date + password after every close; changes to closed periods go through a documented reopen | C17: Prior-period drift is the #1 cause of broken reconciliations | D17: Close checklist step 8
A18: Separation of duties | B18: Brad moves documents and money mechanics; Sarah makes every judgment; neither crosses over | C18: Clean WOSB control story + clean E&O story + no single point of failure in either lane | D18: Role table (Tab 2)
A19: Data security | B19: MFA on everything; client documents through the portal only (never email); encrypted archive; 7-year retention; cyber policy active | C19: The firm holds bank credentials and PII from day one | D19: Onboarding SOP + annual security review
A20: Client file hygiene | B20: Opening Balance Equity must be zero after setup; Undeposited Funds swept in every close; Add-vs-Match verified, never auto-accepted | C20: The three most common silent corruptions in QuickBooks files | D20: Close checklist steps 3-5
A22: Software Stack & Monthly Cost
A23: Tool | B23: Monthly cost | C23: Purpose | D23: Note
A24: Intuit accountant platform (QBOA → Core) | B24: $0 | C24: Firm hub; includes free QBO Advanced + payroll for the firm's own books | D24: Confirm Core (free) tier at Dec 2026 migration — calendar entry exists
A25: Client QBO subscriptions | B25: Firm-billed wholesale | C25: ProAdvisor Preferred Pricing: permanent 30% discount; billed to firm, charged to client in the fixed fee | D25: Blended margin ≈ +$20/client/mo — treated as a rebate, NOT load-bearing profit (Intuit repricing risk)
A26: Document portal + file system | B26: $0-20 | C26: Client upload portal (Brad builds) + Dropbox Business structure | D26: Brad's build; the moat most solo firms lack
A27: QuickBooks Payments (ACH) | B27: ~1% of drafted revenue | C27: The autodraft rail (Tab 4) | D27: Scales with revenue, ~$40-90/mo at 10-14 clients
A28: E&O + cyber insurance | B28: ~$85-120 | C28: Before client #1; claims-made retro date | D28: The largest fixed cost
A29: Password manager, e-sign, scheduling, misc. | B29: ~$20-50 | C29: 1Password, e-signature free tiers → paid, calendar link | D29: Lean by design
A30: TOTAL FIXED STACK | B30: ≈ $105-190/mo net | C30: Full operating cost before labor | D30: Covered by the first client's retainer — the break-even fact in Tab 7
A32: Capacity & Seasonality
A33: Capacity math (1.0 production FTE): ~110 working hours/month, less a ~30% non-delivery reserve for selling, learning, and firm admin, leaves ~77 deliverable hours. New clients cost 8-10 hours/month for the first six months (learning the business, fixing setup) and settle toward ~5 at steady state as Brad's rules and pipelines absorb the mechanical layer — so the ceiling is ~8 clients while all are new and ~15 once the book matures. The plan hires a contract preparer at ~12-14 clients rather than degrading quality. January is the crunch: 1099s due Jan 31, year-end closes, and the Q1 cleanup-demand spike (also the year's best acquisition window). Standing policy: W-9s collected at onboarding all year; new-client onboarding freezes mid-January to mid-February; cleanup projects quoted in Q1 are scheduled, not rushed.
A35: KPI Dashboard (reviewed monthly against the decision gates in Tab 12)
A36: KPI | B36: Target | C36: Why it is on the dashboard
A37: MRR / client count | B37: Gates: 3 clients by day 90; 8-12 by month 12 | C37: The kill-or-continue metric
A38: Hours per client | B38: ≤9 in months 1-6, trending to 5 | C38: The margin metric, and the same figures the Tab 7 model runs on (9 early / 5 steady). If it will not fall, pricing or screening is wrong.
A39: Close-by-day | B39: 100% of closes delivered by the 15th | C39: The service-quality promise clients actually notice
A40: Failed drafts | B40: 0 outstanding past day 10 | C40: AR stays zero by design or the policy is broken
A41: Pipeline conversations | B41: 10/month during growth phases | C41: Leading indicator; revenue problems appear here 90 days early
A42: Review count (Google) | B42: +1 per month minimum | C42: The map-pack currency
A44: Source: Close methodology: practitioner close/cleanup literature (Winnie Jayne 12-step; AccountingCoach adjusting entries; AccountingTools payroll entries); TFRP: IRS guidance; hours-per-client: Jetpack Workflow benchmark + red-team adjustment; ProAdvisor Preferred Pricing: Intuit published terms. Full citations Tab 14.

Sheet 7. Financial Model
A1: FINANCIAL MODEL — INTERACTIVE
A2: Yellow cells are inputs: change them and every calculation updates. Gray cells are live formulas.
A4: Inputs (edit the yellow cells)
A5: Input | B5: Value | C5: Unit | D5: Guidance (why this default)
A6: Average monthly fee — early book | B6: 400 | C6: $/client/mo | D6: Red-team finding: first ten clients close at $350-450. Default $400.
A7: Average monthly fee — mature book | B7: 650 | C7: $/client/mo | D7: Month-12+ blended rate after niche proof and annual price steps.
A8: Hours per client — first 6 months | B8: 9 | C8: hrs/mo | D8: Benchmark 5-6 for experienced firms; new-firm reality is 8-10 while learning each business.
A9: Hours per client — steady state | B9: 5 | C9: hrs/mo | D9: Earned, not assumed: arrives as bank rules and pipelines absorb the mechanical layer.
A10: Working hours per month (1.0 production FTE) | B10: 110 | C10: hrs | D10: Sarah only. Brad's hours build systems and pipeline; they do not close books.
A11: Non-delivery reserve (selling, learning, admin) | B11: 0.3 | C11: % | D11: The hours an owner-operator cannot bill: prospecting, CPA relationships, certification, firm admin. Industry read: year-one delivery capacity is 60-80% of the theoretical ceiling. Set to 0% only for a mature firm with a full pipeline and no learning curve.
A12: Annual client retention (yrs 1-2) | B12: 0.8 | C12: % | D12: Small firms typically retain 60-70%; well-run firms 90-96%. Honest new-firm band: 75-85%.
A13: Fixed cost — E&O + cyber insurance | B13: 100 | C13: $/mo | D13: ~$1,000-1,400/yr bound before client #1 (claims-made retroactive date).
A14: Fixed cost — software & tools | B14: 60 | C14: $/mo | D14: Net of ProAdvisor wholesale margin on client subscriptions (treated as rebate, not profit).
A15: Fixed cost — misc (domain, phone, filings) | B15: 30 | C15: $/mo | D15: Lean by design.
A16: ACH processing fee | B16: 0.01 | C16: % of revenue | D16: QuickBooks Payments ACH ≈1%. Melio fallback is $0.
A17: Average cleanup project | B17: 2500 | C17: $ | D17: Cleanup prices at 2-2.5x monthly rate per month of mess; 12-month cleanups run 40-60 hours.
A19: What Falls Out (live formulas — recalculate when inputs change)
A20: Result | B20: Value | C20: Unit | D20: How it is computed / what it means
A21: Total fixed costs | B21: =B13+B14+B15 -> 190 | C21: $/mo | D21: Insurance + software + misc. The entire cost base before labor.
A22: BREAK-EVEN CLIENT COUNT (early pricing) | B22: =CEILING(B21/(B6*(1-B16)),1) -> 1 | C22: clients | D22: Fixed costs ÷ net early fee, rounded up. The number the whole document was asked to produce: at defaults, the FIRST client covers every fixed cost.
A23: Deliverable hours per month (after reserve) | B23: =B10*(1-B11) -> 77 | C23: hrs | D23: Working hours less the non-delivery reserve. This — not the 110 — is what actually closes books.
A24: CAPACITY CEILING — steady state | B24: =FLOOR(B23/B9,1) -> 15 | C24: clients | D24: Deliverable hours ÷ steady hours per client. Quality breaks past this without a hire. This is the number behind every "solo ceiling" claim in the plan.
A25: Capacity ceiling — first-6-months pace | B25: =FLOOR(B23/B8,1) -> 8 | C25: clients | D25: Same ceiling at new-client hours — why onboarding is paced, not maximized. This is the binding constraint during the ramp.
A26: Solo ceiling ARR (mature pricing) | B26: =B24*B7*12 -> 117000 | C26: $/yr | D26: The honest solo revenue ceiling before hiring. Price moves clients-needed, not the ceiling.
A27: Expected client lifetime | B27: =1/(1-B12) -> 5 | C27: years | D27: Geometric expectation at the retention input.
A28: Lifetime value (LTV, mature fee) | B28: =B7*12*(1/(1-B12))*(1-B16) -> 38610 | C28: $ | D28: Fee × lifetime, net of processing. At defaults ≈ $39k gross potential; the plan's conservative planning figure is $15-20k until retention is demonstrated.
A29: Monthly net at break-even +1 client | B29: =2*B6*(1-B16)-B21 -> 602 | C29: $/mo | D29: What two early clients net after all fixed costs.
A31: Income by Client Count (live table)
A32: Clients | B32: Revenue/mo (early $) | C32: Revenue/mo (mature $) | D32: Hours needed (steady) | E32: Capacity check | F32: Firm profit/mo (mature) — PRE-TAX, PRE-OWNER-PAY
A33: 1 | B33: =A33*B6 -> 400 | C33: =A33*B7 -> 650 | D33: =A33*B9 -> 5 | E33: =IF(A33*B9>B23,"OVER — hire required",IF(A33*B8>B23,"OK (tight during ramp)","OK")) -> OK | F33: =A33*B7*(1-B16)-B21 -> 453.5
A34: 2 | B34: =A34*B6 -> 800 | C34: =A34*B7 -> 1300 | D34: =A34*B9 -> 10 | E34: =IF(A34*B9>B23,"OVER — hire required",IF(A34*B8>B23,"OK (tight during ramp)","OK")) -> OK | F34: =A34*B7*(1-B16)-B21 -> 1097
A35: 4 | B35: =A35*B6 -> 1600 | C35: =A35*B7 -> 2600 | D35: =A35*B9 -> 20 | E35: =IF(A35*B9>B23,"OVER — hire required",IF(A35*B8>B23,"OK (tight during ramp)","OK")) -> OK | F35: =A35*B7*(1-B16)-B21 -> 2384
A36: 6 | B36: =A36*B6 -> 2400 | C36: =A36*B7 -> 3900 | D36: =A36*B9 -> 30 | E36: =IF(A36*B9>B23,"OVER — hire required",IF(A36*B8>B23,"OK (tight during ramp)","OK")) -> OK | F36: =A36*B7*(1-B16)-B21 -> 3671
A37: 8 | B37: =A37*B6 -> 3200 | C37: =A37*B7 -> 5200 | D37: =A37*B9 -> 40 | E37: =IF(A37*B9>B23,"OVER — hire required",IF(A37*B8>B23,"OK (tight during ramp)","OK")) -> OK | F37: =A37*B7*(1-B16)-B21 -> 4958
A38: 10 | B38: =A38*B6 -> 4000 | C38: =A38*B7 -> 6500 | D38: =A38*B9 -> 50 | E38: =IF(A38*B9>B23,"OVER — hire required",IF(A38*B8>B23,"OK (tight during ramp)","OK")) -> OK (tight during ramp) | F38: =A38*B7*(1-B16)-B21 -> 6245
A39: 12 | B39: =A39*B6 -> 4800 | C39: =A39*B7 -> 7800 | D39: =A39*B9 -> 60 | E39: =IF(A39*B9>B23,"OVER — hire required",IF(A39*B8>B23,"OK (tight during ramp)","OK")) -> OK (tight during ramp) | F39: =A39*B7*(1-B16)-B21 -> 7532
A40: 14 | B40: =A40*B6 -> 5600 | C40: =A40*B7 -> 9100 | D40: =A40*B9 -> 70 | E40: =IF(A40*B9>B23,"OVER — hire required",IF(A40*B8>B23,"OK (tight during ramp)","OK")) -> OK (tight during ramp) | F40: =A40*B7*(1-B16)-B21 -> 8819
A41: 16 | B41: =A41*B6 -> 6400 | C41: =A41*B7 -> 10400 | D41: =A41*B9 -> 80 | E41: =IF(A41*B9>B23,"OVER — hire required",IF(A41*B8>B23,"OK (tight during ramp)","OK")) -> OVER — hire required | F41: =A41*B7*(1-B16)-B21 -> 10106
A42: 20 | B42: =A42*B6 -> 8000 | C42: =A42*B7 -> 13000 | D42: =A42*B9 -> 100 | E42: =IF(A42*B9>B23,"OVER — hire required",IF(A42*B8>B23,"OK (tight during ramp)","OK")) -> OVER — hire required | F42: =A42*B7*(1-B16)-B21 -> 12680
A43: Reading this table: the $3,000/month household target is crossed at 8 early-priced clients or 5-6 mature-priced clients. The capacity column reads the ceiling honestly in two stages — "tight during ramp" marks counts that fit only once clients mature to steady-state hours, and "OVER" marks counts that need the contract preparer regardless. At the default 30% non-delivery reserve, the practical solo ceiling is ~15 clients, and roughly 8 while every client is still new. WHAT THE LAST COLUMN IS NOT: it is firm profit before any tax and before either owner is paid. Labor is not a cost line because both operators are owners, so the real "cost" of their time is the fallback salary they forgo (priced in Tab 12). To get to household cash, subtract self-employment tax of roughly 15.3% on 92.35% of profit, then federal income tax on what remains after the 20% QBI deduction — call it 22-28% of firm profit in total at these levels, with no Texas income tax. At the 15-client ceiling that turns roughly $9,460/month of firm profit into roughly $6,800-7,400/month of household cash before any health-insurance cost.
A45: Source: Model structure: fixed costs from Tab 6 stack; pricing bands from Ignition 2025/26 benchmark (n=219) + six DFW firm pages; hours from Jetpack Workflow benchmark, red-team adjusted; retention from SmartFirm/Agiled compilations. Every input is editable — the defaults are the defended case.

Sheet 8. Projections
A1: PROJECTIONS — YEAR 1 MONTHLY, YEARS 2-3 SCENARIOS
A2: Yellow cells (new clients, avg fee, cleanup $) are editable; everything else recalculates.
A4: Model Settings (LINKED to Tab 7 — edit them there, not here)
A5: Fixed costs $/mo | B5: ='7. Financial Model'!B21 -> 190 | D5: ACH fee % | E5: ='7. Financial Model'!B16 -> 0.01 | G5: These two cells are live links to Tab 7, so changing an input there flows through this whole tab. Assumption: zero churn modeled inside Y1 (small-number effect); churn is priced into the Y2-3 net client counts below.
A7: Year 1, Month by Month (launch = certification complete)
A8: Month | B8: New clients | C8: Total clients | D8: Avg fee $ | E8: Recurring rev | F8: Cleanup rev | G8: Total revenue | H8: Costs | I8: Net income
A9: M1 | B9: 1 | C9: =B9 -> 1 | D9: 400 | E9: =C9*D9 -> 400 | F9: 0 | G9: =E9+F9 -> 400 | H9: =$B$5+G9*$E$5 -> 194 | I9: =G9-H9 -> 206
A10: M2 | B10: 1 | C10: =C9+B10 -> 2 | D10: 400 | E10: =C10*D10 -> 800 | F10: 2500 | G10: =E10+F10 -> 3300 | H10: =$B$5+G10*$E$5 -> 223 | I10: =G10-H10 -> 3077
A11: M3 | B11: 1 | C11: =C10+B11 -> 3 | D11: 400 | E11: =C11*D11 -> 1200 | F11: 0 | G11: =E11+F11 -> 1200 | H11: =$B$5+G11*$E$5 -> 202 | I11: =G11-H11 -> 998
A12: M4 | B12: 0 | C12: =C11+B12 -> 3 | D12: 400 | E12: =C12*D12 -> 1200 | F12: 2500 | G12: =E12+F12 -> 3700 | H12: =$B$5+G12*$E$5 -> 227 | I12: =G12-H12 -> 3473
A13: M5 | B13: 1 | C13: =C12+B13 -> 4 | D13: 400 | E13: =C13*D13 -> 1600 | F13: 0 | G13: =E13+F13 -> 1600 | H13: =$B$5+G13*$E$5 -> 206 | I13: =G13-H13 -> 1394
A14: M6 | B14: 1 | C14: =C13+B14 -> 5 | D14: 400 | E14: =C14*D14 -> 2000 | F14: 2500 | G14: =E14+F14 -> 4500 | H14: =$B$5+G14*$E$5 -> 235 | I14: =G14-H14 -> 4265
A15: M7 | B15: 1 | C15: =C14+B15 -> 6 | D15: 425 | E15: =C15*D15 -> 2550 | F15: 0 | G15: =E15+F15 -> 2550 | H15: =$B$5+G15*$E$5 -> 215.5 | I15: =G15-H15 -> 2334.5
A16: M8 | B16: 0 | C16: =C15+B16 -> 6 | D16: 425 | E16: =C16*D16 -> 2550 | F16: 2500 | G16: =E16+F16 -> 5050 | H16: =$B$5+G16*$E$5 -> 240.5 | I16: =G16-H16 -> 4809.5
A17: M9 | B17: 1 | C17: =C16+B17 -> 7 | D17: 425 | E17: =C17*D17 -> 2975 | F17: 0 | G17: =E17+F17 -> 2975 | H17: =$B$5+G17*$E$5 -> 219.75 | I17: =G17-H17 -> 2755.25
A18: M10 | B18: 1 | C18: =C17+B18 -> 8 | D18: 450 | E18: =C18*D18 -> 3600 | F18: 2500 | G18: =E18+F18 -> 6100 | H18: =$B$5+G18*$E$5 -> 251 | I18: =G18-H18 -> 5849
A19: M11 | B19: 0 | C19: =C18+B19 -> 8 | D19: 450 | E19: =C19*D19 -> 3600 | F19: 0 | G19: =E19+F19 -> 3600 | H19: =$B$5+G19*$E$5 -> 226 | I19: =G19-H19 -> 3374
A20: M12 | B20: 1 | C20: =C19+B20 -> 9 | D20: 450 | E20: =C20*D20 -> 4050 | F20: 2500 | G20: =E20+F20 -> 6550 | H20: =$B$5+G20*$E$5 -> 255.5 | I20: =G20-H20 -> 6294.5
A21: YEAR 1 | B21: =SUM(B9:B20) -> 9 | E21: =SUM(E9:E20) -> 26525 | F21: =SUM(F9:F20) -> 15000 | G21: =SUM(G9:G20) -> 41525 | H21: =SUM(H9:H20) -> 2695.25 | I21: =SUM(G9:G20)-SUM(H9:H20) -> 38829.75
A22: Cash equals accrual in this model: every retainer drafts on the 1st in advance, cleanup takes a 50% deposit at signing, and the firm carries zero receivables — so the net income line IS the cash line, less only owner draws. The client-add pattern above deliberately passes each decision gate (3 by month 3, 5 by month 6, 9 by month 12); the gates and what happens on a miss live in Tab 12.
A24: Years 2-3 Scenarios (annual view; churn priced in via net adds)
A25: Scenario | B25: End Y2 clients | C25: Y2 avg fee $ | D25: Y2 total revenue | E25: End Y3 clients | F25: Y3 avg fee $ | G25: Y3 total revenue | H25: Y3 firm profit — PRE-TAX, PRE-OWNER-PAY | I25: Requires
A26: Conservative | B26: 10 | C26: 500 | D26: =B26*C26*12*0.92+15000 -> 70200 | E26: 12 | F26: 550 | G26: =E26*F26*12*0.92+20000 -> 92864 | H26: =G26-'7. Financial Model'!B21*12-IF(E26>'7. Financial Model'!B24,E26*12*90,0) -> 90584 | I26: No hire; referrals only; retention 75%. Sits inside the 15-client solo ceiling in both years.
A27: Moderate | B27: 13 | C27: 550 | D27: =B27*C27*12*0.92+15000 -> 93936 | E27: 15 | F27: 650 | G27: =E27*F27*12*0.92+20000 -> 127640 | H27: =G27-'7. Financial Model'!B21*12-IF(E27>'7. Financial Model'!B24,E27*12*90,0) -> 125360 | I27: Ends Y3 exactly at the 15-client solo ceiling computed in Tab 7; the hire decision is live but not yet taken.
A28: Optimistic | B28: 16 | C28: 600 | D28: =B28*C28*12*0.92+15000 -> 120984 | E28: 22 | F28: 700 | G28: =E28*F28*12*0.92+20000 -> 190016 | H28: =G28-'7. Financial Model'!B21*12-IF(E28>'7. Financial Model'!B24,E28*12*90,0) -> 163976 | I28: Crosses the ceiling during Y2 (16 > 15), so the contract preparer is hired in Y2, not Y3. Y2 revenue is shown GROSS of that labor cost; only the Y3 profit column charges it.
A29: FORMULA, SPELLED OUT. Revenue = (ending clients) x (avg fee) x 12 x 0.92 + cleanup ($15k Y2 / $20k Y3). Worked example, Moderate Y2: 13 x $550 x 12 = $85,800, x 0.92 = $78,936, + $15,000 cleanup = $93,936. The profit column subtracts annual fixed costs (linked live from Tab 7) and, above the Tab 7 capacity ceiling, contract-preparer labor at ~$90 per client-month. WHAT THE 0.92 ASSUMES, STATED PLAINLY. It converts an ending client count into an average one, because this table has no month detail the way the Year 1 table above does. A 0.92 factor against 13 ending clients implies an average of about 12.0 across the year. Starting from 9 clients at the end of Year 1, a straight-line ramp to 13 would average 11.0, which is a factor of about 0.85. So 0.92 assumes Year 2 additions are front-loaded into the first four or five months, which is the intent (Year 1 exits with a filled pipeline and referral momentum) but is an assumption, not a fact. Setting the factor to 0.85 instead reduces Moderate Y2 revenue by roughly $6,700. That is the honest sensitivity, and it is the kind of thing worth arguing about. PRE-TAX, PRE-OWNER-PAY. The profit column is before tax and before either owner is paid. Expect 22-28% to self-employment and federal income tax after the QBI deduction, with no Texas income tax. Crossover test: Tab 12 shows the DFW corporate path; this firm beats it on money alone only if MRR reaches ~$15-20k by month 30-36. Below that, the honest justification is autonomy, household fit, and the sellable asset.
A31: Source: Ramp pattern satisfies the decision gates (Tab 12); realization factor and preparer cost from AICPA CAS benchmark ranges; cleanup volumes front-loaded per practitioner literature (Q1 spike). All yellow cells editable.

Sheet 9. Startup & Deployment
A1: STARTUP CAPITAL & DEPLOYMENT
A2: What it costs to start, the launch sequence, and the honest solvency statement
A4: Startup Costs (entity, EIN, and bank already exist — $0 shown where already owned)
A5: Item | B5: Cost | C5: Detail | D5: Timing
A6: LLC / EIN / business bank | B6: $0 | C6: The Relief Pros, LLC exists, compliant, and empty — no formation costs remain | D6: Done
A7: QuickBooks ProAdvisor certification | B7: $0 | C7: Free program; free training; free QBO Advanced for the firm's own books | D7: Weeks 1-3
A8: Study materials | B8: $0-99 | C8: AccountingCoach free tier covers fundamentals; PRO upgrade $99/yr optional | D8: Weeks 1-6
A9: Xero Advisor Level 1 | B9: $0 | C9: Platform hedge | D9: Week 3
A10: E&O + cyber insurance (first months) | B10: ~$200-300 | C10: First premium payments; ~$1,000-1,400/yr total; bound BEFORE client #1 | D10: Before first engagement
A11: Domain + site + portal hosting | B11: ~$50-100 | C11: Brad builds on existing infrastructure and skills | D11: Weeks 2-6
A12: Engagement letter template (attorney review) | B12: $0-250 | C12: One-time review of scope/ACH/no-payment-authority clauses; templates exist | D12: Week 4-6
A13: Operating-agreement language check | B13: $0-150 | C13: One-hour attorney confirmation that Sarah's 100% ownership and control language is WOSB-ready | D13: Before WOSB filing
A14: TOTAL CASH TO LAUNCH | B14: Under $700 | C14: The complete number. No loan, no office, no employees, no inventory. | D14: —
A16: Launch Sequence (first 90 days, two lanes running in parallel)
A17: Weeks | B17: Sarah (skills & certification lane) | C17: Brad (infrastructure lane) | D17: Gate
A18: 1-3 | B18: AccountingCoach fundamentals; QBO Level 1 via coursework; practice file opened in QBOA "Your Books" | C18: Domain, site skeleton, Google Business Profile claimed, Dropbox/portal structure designed | D18: Level 1 passed; directory profile live
A19: 4-6 | B19: Close-checklist drills in the practice sandbox; deliberately wreck and clean a practice file (12-step order); Xero L1 | C19: Portal live; ACH rail enrolled and tested with a $1 draft; engagement letter + ACH authorization finalized; review-request system built | D19: One full simulated close executed cleanly
A20: 7-9 | B20: First 2-3 warm-network books at reduced fee, CPA-reviewed; diagnostic template built; niche demo workflows (job costing, POS) built | C20: New-filing scraper running; outreach lists built; citation/directory profiles seeded | D20: First real close delivered; testimonial #1 requested
A21: 10-13 | B21: Validation sprint in full swing: CPA lunches, trade associations, proposals | C21: SEO pages per niche/suburb; review engine running | D21: SPRINT GATE: 30 conversations / 10 proposals / 3 signed clients
A23: The Honest Solvency Statement (red-team finding adopted)
A24: The $700 startup figure is true for the entity but is not a solvency statement — the binding constraint is household runway, not business capitalization. This household's structural advantage: VA disability compensation is a fixed, inflation-adjusted, employment-independent income floor that most two-founder households do not have, so the household is never 100% dependent on the firm's ramp. The plan's standing rule: if household reserves plus fixed income cover less than 9-12 months of expenses at any point, Sarah's job search runs in parallel with the launch (the fallback market is liquid — Tab 12) rather than after it. Nothing about this plan requires burning savings to find out if it works; the 90-day sprint answers that for under $700.
A26: Optional Accelerators (not required; deploy only after the sprint gate passes)
A27: Item | B27: Cost | C27: What it buys | D27: When
A28: Ignition (proposals + payments) | B28: ~$39-99/mo | C28: Professional proposal-to-payment flow | D28: At ~10 clients
A29: AIPB workbook set | B29: $254-314 | C29: The trade's best self-study depth (adjusting entries, error correction, payroll entries) | D29: Months 3-6, as training material
A30: Community college Accounting I-II | B30: ~$300-600 | C30: The practitioner-consensus foundation if Sarah wants formal reps | D30: Optional, evenings
A31: Paid ads experiment | B31: $300-500 cap | C31: One controlled test of a niche landing page | D31: Only after referral channels saturate
A33: Source: Insurance: Insureon/Next published medians for bookkeepers; ProAdvisor program terms: Intuit (verified free, July 2026 archive); study-path costs: AccountingCoach, AIPB bookstore, Dallas College published tuition. Full citations Tab 14.

Sheet 10. SWOT & Risk Register
A1: SWOT & RISK REGISTER
A2: The four-quadrant view, then every material risk with mitigation and tripwire
A4: SWOT
A5: Quadrant | C5: Contents
A6: STRENGTHS | C6: MBA-grade judgment on the delivery side paired with rare automation/web capability on the ops side; near-zero fixed costs; zero-AR cash model; existing clean entity; VA income floor under the household; no need to price against the collapsed low end
A7: WEAKNESSES | C7: Zero bookkeeping track record (certification is a tool credential, not proof of competency); one production FTE — the firm IS Sarah; unproven sales appetite; no testimonials at launch; early pricing power is weak ($350-450)
A8: OPPORTUNITIES | C8: CPA firms shedding write-up work (labor shortage, graduates -6.6% YoY); low-end national providers dead or retreating; retiring solo bookkeepers = future book acquisitions; niche premium (+51% revenue/client, AICPA); Q1 cleanup season each year
A9: THREATS | C9: Intuit platform/pricing power and its AI "done-for-you" ambitions; client mortality in chosen niches; recession flattening (2009 CPA fees +0.6%, not growth); commoditization at the data-entry layer; a serious local competitor professionalizing first
A11: Risk Register (likelihood × impact, with named tripwires)
A12: Risk | B12: L × I | C12: Mitigation | D12: Tripwire (act when...)
A13: Key person: Sarah out 6+ weeks | B13: Low × Severe | C13: Documented per-client close checklists from client #1 (also enables hiring and sale); Brad cross-trained on mechanics; own-occupation disability insurance once revenue justifies | D13: Any health signal → engage backup bookkeeper relationship (build one by month 6)
A14: Sales appetite / conversion unproven | B14: Med × High | C14: 90-day validation sprint with numeric kill criteria; white-label fallback needs almost no selling | D14: Sprint gate missed → pivot to subcontract model within 30 days
A15: Client mortality in niches | B15: High × Med | C15: Restaurants capped 25%; prefer 2yr+ businesses; third stickier niche (professional services) as ballast | D15: Roster churn >20%/yr → rebalance niches before growing
A16: Intuit repricing / platform squeeze | B16: Med × Med | C16: Wholesale margin treated as rebate, never profit; pass-through billing design; Xero L1 maintained as credible exit | D16: ProAdvisor discount cut → shift new clients to client-billed retail within one quarter
A17: AI "done-for-you" leapfrog | B17: Low-Med × High | C17: Firm already operates AI-forward (automation inside, judgment out); niches chosen where books resist full automation (job costing, POS/tips) | D17: Intuit ships an autonomous bookkeeping product with traction → accelerate advisory-tier move
A18: Scope creep on fixed fees | B18: High × Med | C18: Engagement-letter scope armor; separate line items; change orders for anything new; annual price step | D18: Any client at >8 steady-state hours for 2 straight months → reprice or exit them
A19: Texas data-processing tax drift | B19: Low × Med | C19: Payroll/AP/AR excluded at launch; services invoiced as separate lines; annual CPA check on the 2025 rule's automation boundary | D19: Comptroller guidance names automated bookkeeping → collect-and-remit from next invoice
A20: Data breach / credential theft | B20: Low × Severe | C20: Portal-only documents, MFA everywhere, cyber policy, 7-year encrypted archive | D20: Any incident → carrier notice within 24h per policy
A21: WOSB control-test failure | B21: Low × Low-Med | C21: Sarah is 100% owner; operating-agreement language check before filing; this plan's role wording already written for examiners | D21: SBA questions control → attorney letter within the response window
A22: January capacity crunch | B22: Certain × Med | C22: W-9s at onboarding; 1099s priced as January fee; onboarding freeze mid-Jan to mid-Feb; cleanup quoted-not-rushed | D22: Close-by-day slips in January → freeze extends to March 1
A23: Household income concentration | B23: Med × High | C23: VA floor + Sarah's maintained employability (network, credentials kept warm) + solo-401k assets outside the firm | D23: Reserves under 9 months → parallel job search activates (standing rule, Tab 9)
A24: E&O claim | B24: Low × High | C24: Claims-made policy bound before client #1 with clean retro date; no tax advice; documented review trail; tail coverage on any wind-down | D24: Any client dispute in writing → carrier notice immediately, before resolution attempts
A26: What This Register Deliberately Admits
A27: Three assumptions in this plan are triangulated rather than measured, and no citation can fix that: (1) hours-per-client is an industry benchmark, not this firm's measured number — the model prices the pessimistic end until real data exists; (2) no reliable survey of solo-firm revenue exists — the ceiling math is built from hours and rates, not from a published distribution; (3) retention benchmarks come from industry compilations of uneven quality — which is why the model runs at 75-85%, the honest band, not the 95% the industry content repeats. Where the evidence is anecdotal (practitioner threads), it is labeled anecdotal in Tab 14.
A29: Source: Recession behavior: CPA Trendlines 2009 fee data; Intuit COVID-19 practitioner survey; niche mortality: Owner.com/LendingTree closure analyses; platform risk: Intuit SEC 8-K + ProAdvisor program history; TFRP and tax-drift: IRS + Texas Comptroller. Full citations Tab 14.

Sheet 11. Certifications & Growth
A1: CERTIFICATIONS & GROWTH PROGRAMS
A2: The women-owned path, stated honestly — then the acquisition strategy for buying books of business
A4: Material Change Disclosed First: Texas Ended Its Women/Minority HUB Program
A5: On December 2, 2025, the Texas Comptroller restructured the Historically Underutilized Business program into "VetHUB," which now serves only businesses 51%-owned and controlled by service-disabled veterans (20%+ rating). All certifications based on sex, race, or ethnicity were revoked. The state-level women-owned certification this plan would otherwise have pursued no longer exists. The program runs on emergency rules with litigation ongoing. This plan proceeds on the women-owned path anyway, for the reasons in the "considered and declined" box below — but the change is disclosed here because a plan that hid it would fail the first stress-test question.
A7: Certifications Available to This Firm (Sarah, 100% owner)
A8: Certification | B8: Cost / time | C8: What it actually delivers (evidence) | D8: Verdict
A9: SBA WOSB (federal) | B9: Free via MySBA; ~90 days to decide (13 CFR 127.304(a)); then ~0.5 hr every 3 years | C9: Honest dollar data (USAspending API, NAICS 541219): WOSB set-asides were $1.1M-$1.5M/yr FY23-24 and NET NEGATIVE in FY25. Eligibility has not translated into dollars in this code. Value = credibility marker + long-term option, not a channel. | D9: FILE IT — it is free; expect $0 near-term revenue from it
A10: SAM.gov registration | B10: Free; renews every 365 days; ~2.6-3 hrs/yr | C10: Prerequisite for any government work ever. Registration expires at 365 days and must be actively renewed or it lapses, taking WOSB eligibility with it. FAR 4.1201(b)(1) and clause 52.204-13 require an annual review and update of the registration and its representations and certifications. The 2.6-3 hour figure is the government's own Paperwork Reduction Act burden estimate, not a guess. Allow 10 business days to go active, so start ~60 days early. Renewal is free — anyone charging for it is not a government service. | D10: Calendar renewal at day 305 each year
A11: WOSB ongoing maintenance | B11: $0 cash; ~0.5 hr every 3 years | C11: TRIENNIAL, not annual. Under 13 CFR 127.400 a certified firm undergoes a program examination every three years, and must recertify or report a third-party examination within the 90 days before its eligibility period ends (30-day reinstatement grace after that). The annual attestation that used to apply was repealed effective May 30, 2023 (88 FR 26214) and SBA has it in abeyance. Program examinations are conducted by SBA at no cost — no paid outside auditor is required. Standing duty in between: notify SBA in writing within 30 days of any material change in ownership, structure, or management (13 CFR 127.401). | D11: Calendar recertification at 2 yrs 9 months; keep an eligibility file current
A12: NCTRCA / City of Dallas M/WBE | B12: Modest fees; ~60-90 days | C12: City of Dallas still recognizes M/WBE for municipal contracting, though the statewide direction of travel is against sex-based programs | D12: File when a municipal prospect exists, not before
A13: WBENC (private/corporate) | B13: $350/yr under $1M revenue | C13: Corporate supplier-diversity channel; retrenching nationally (200+ S&P 500 firms scrubbed DEI language) but actual diverse-supplier spend hit record highs in 2024 under "supplier inclusion" rebrands | D13: Only if a specific corporate prospect asks
A14: Texas VetHUB | B14: Free; up to 90 days | C14: The only remaining state certification — requires 51% service-disabled-veteran ownership AND control | D14: NOT AVAILABLE under current structure — see declined box
A16: Considered and Declined: Restructuring for the Veteran Certification Stack
A17: The research is presented in full because the reviewer should see the road not taken. Federal SDVOSB set-asides in this exact NAICS code ran $19-28M/yr (15-25x the WOSB dollars), with sole-source authority to $4.5M and VA "Vets First" preference. SBA rules (13 CFR 128.203) even allow the spouse of a permanently-and-totally disabled veteran to control the company day-to-day. Reaching it would require restructuring to Brad owning 51%. DECLINED, for three reasons: (1) the household deliberately structured this LLC under Sarah's ownership, and that decision is settled; (2) the veteran route carries verification burdens and, depending on rating type, risk to disability status that money cannot justify; (3) the entire government channel — either flavor — is a year-3+ option for a two-person firm with no past performance, so the foregone dollars are speculative. Veteran identity still helps where it needs no ownership: "veteran-family business" is honest DFW marketing language, and veteran business networks are open doors.
A19: Expansion Strategy: Buying Books of Business (Phase 2 — year 3+, zero weight in the base case)
A20: Element | B20: Market data | C20: Detail | D20: Rule adopted
A21: What sells | B21: Bookkeeping firms: ~1.0-1.2x annual collections; 2.55-3.32x SDE; write-up books at the 0.7-1.0x low end | C21: Retiring solo practitioners are the supply — the same BLS replacement wave documented in Tab 3 | D21: Target off-market solo books, 0.8-1.2x
A22: How deals are structured | B22: Seller financing + retention-based earnout is standard | C22: Buyer pays as clients actually stay (1-2 years); clawback protects against transfer churn — sellers finance because transfer retention is the real risk | D22: Never pay cash up front for relationships
A23: Where to look | B23: Accounting Practice Sales, Poe Group Advisors, BizBuySell + direct mail to bookkeepers 60+ in DFW | C23: Off-market direct outreach avoids competitive bidding on listed practices | D23: Brad runs the sourcing list like the lead lists
A24: Readiness gate | B24: Transferred clients churn hardest in year one; a buyer under 2 years old compounds it | C24: The firm earns the right to buy by demonstrating its OWN retention above ~90% and clean financials for 2 years | D24: No acquisition before month 24; zero weight in projections
A25: What $50k buys (illustration) | B25: A ~$50k-collections book at 1.0x, seller-financed over 2 years from the book's own cash flow | C25: ≈8-10 clients arriving at once — a year of organic growth in one signature, funded by operating cash | D25: Phase 2 financing plan; revisit at gate
A26: Buy-side vs sell-side (do not confuse them) | B26: Buy 0.8-1.2x · Sell (this firm, young) 0.5-0.8x realized · Sell (mature, staffed) 1.0-1.4x+ | C26: These are different numbers for different situations and the plan uses both deliberately. Acquiring another practitioner's book is a negotiation where paying less is the goal. Selling THIS firm early means selling a young, owner-dependent book, which takes a real discount. A matured firm with documented processes, a preparer on staff, and 90%+ retention sells at the higher end — which is the argument for building the close checklists from client #1. | D26: Both figures stated where used
A28: The Service Ladder Beyond the Ceiling (year 3+ options, each costed in earlier tabs)
A29: Three levers stack past the $117k solo ceiling: (1) the contract-preparer hire at ~12-14 clients (Tab 8 optimistic case); (2) the service ladder — payroll administration (with sales tax collected and NO payment authority), then controller-level review at $2,000-8,000/mo per client, the natural landing zone for an MBA and the fractional path where 3-4 clients replicate a corporate salary at part-time hours; (3) acquired books, above. None is required for the base case; all three are how $110k becomes $200k+ if the household wants it to.
A31: Source: VetHUB: Texas Comptroller + Texas Tribune (Dec 2, 2025); set-aside dollars: USAspending.gov API pulls FY2023-25, NAICS 541219; 13 CFR 127/128 (eCFR); WBENC fees: WBEC published schedules; practice multiples: Peak Business Valuation + Accounting Practice Sales; fractional rates: NerdWallet + vendor guides (triangulated). Full citations Tab 14.

Sheet 12. Exit & Fallback
A1: EXIT STRATEGIES & JOB-MARKET FALLBACK
A2: If it fails: how it unwinds, what survives, and why the attempt is not wasted
A4: Decision Gates (set now, before feelings are involved)
A5: Gate | B5: Threshold | C5: If missed | D5: Principle
A6: Day 90 | B6: 3 signed clients (30 conversations, 10 proposals) | C6: Diagnose channel, not effort; pivot niche or pivot to white-label subcontracting within 30 days | D6: The sprint is a test, not a verdict on the household
A7: Month 6 | B7: 3-5 clients, ~$1,500-2,500 MRR | C7: Yellow: secure a CPA-overflow subcontract relationship as income bridge + supervised reps | D7: Exit options degrade slowly, not suddenly
A8: Month 12 | B8: 8-12 clients, ~$4,000-6,000 MRR | C8: Red: begin tuck-in/employment conversations while the book still has sale value | D8: A shrinking book is worth more sold early
A9: Month 18 | B9: Net income within reach of the $72k full-charge floor | C9: Execute exit: sell or merge the book, take employment | D9: Every gate exits into the salary table below, not into zero
A10: Month 30-36 | B10: $15-20k MRR trajectory | C10: Below this, the firm loses to the corporate path on money alone — continue only for autonomy, household fit, and the sellable asset, and say so out loud | D10: The crossover test, named honestly
A12: Wind-Down Mechanics (60-90 days, contractual not regulatory — no license exists to surrender)
A13: Step | B13: Cost | C13: Detail
A14: Client termination letters | B14: $0 | C14: 30 days' notice per engagement letter, delivery proof, all committed work completed through termination — corner-cutting at the end is the malpractice pattern
A15: Records return & retention | B15: Under $100 | C15: Source documents returned; portal access closed; firm workpapers archived encrypted 7 years (industry standard; IRS preparer minimum is 3)
A16: Tail insurance | B16: Few hundred $/yr, 1-2 years | C16: E&O claims arrive after the work ends; tail coverage closes the exposure
A17: Entity disposition | B17: $0 or $40 | C17: Keep the LLC dormant at ~$0/yr (below franchise threshold) as a restart option, or terminate ($40 SOS fee + final franchise filing)
A18: Book sale (see below) | B18: Proceeds, not cost | C18: Even a 5-client book has a buyer
A20: What a Small Book Sells For (failure-scale math)
A21: Bookkeeping practices trade at ~1.04-1.17x revenue (2.55-3.32x SDE); young owner-dependent books take a 0.2-0.4x haircut. Realistic failure-scale example: 10 clients × $400/mo = $48k annual collections; a sale at 0.5-0.8x on a collections-based earnout yields roughly $24-38k, paid over 1-2 years as clients stay. Buyers at this scale exist in numbers: local CPA firms wanting recurring write-up work, other solo bookkeepers, and PE-backed platforms doing tuck-ins. The frequently-better alternative: the TUCK-IN — sell the book to a firm that also hires Sarah, converting the practice into a Dallas-market salary plus a book payment. Failed practices in this trade convert into jobs; that conversion is the real downside protection.
A23: Job-Market Fallback: DFW Salaries the Practice Experience Feeds Into (2026 data)
A24: Role | B24: DFW pay | C24: Source | D24: Fit
A25: Bookkeeper (all, median) | B25: $51,720 | C25: BLS OEWS May 2025 (API) | D25: The floor, not the target
A26: Full-charge bookkeeper | B26: $71,820-$94,050 | C26: Robert Half 2026 Dallas guide | D26: IMMEDIATE fit after 12-18 months of practice: "MBA who ran P&L for 10 small businesses"
A27: Accounting manager | B27: $110,295-$145,350 | C27: Robert Half 2026 Dallas | D27: 1-2 years of practice + MBA
A28: Assistant controller | B28: $107,160-$161,880 | C28: Robert Half 2026 Dallas/Fort Worth | D28: Small companies prize hands-on QBO + management judgment — exactly what the practice builds
A29: Controller (small/mid co.) | B29: ~$125,600-$216,200 | C29: Built In / Glassdoor DFW (directional) | D29: The 4-6 year ladder top
A30: FP&A manager | B30: $105,000-$150,000+ (national) | C30: Finance Alliance guide | D30: MBA-native track; gap to close is Excel/Power BI modeling, not accounting
A31: Financial manager (all, median) | B31: $169,200 | C31: BLS OEWS May 2025 DFW | D31: The occupation grows +5% while bookkeeping clerks decline — the ladder points at the growing tier
A32: Market liquidity check (July 2026): ~1,100 bookkeeping postings live in DFW on Indeed alone; Robert Half maintains a dedicated remote feed. Self-employment counts as real experience when documented (formal role, P&Ls, client references, clean testimonials) — the plan archives these from day one. The MBA is not diluted by the detour: operational finance tracks explicitly value accounting-side entrants, and "has actually closed books" beats "has only modeled them" at small-company controller level. The only track the practice does not feed is investment banking, which was never the realistic path from DFW small-business work.
A34: Sunk-Cost Accounting of a Failed Attempt
A35: Recoverable | C35: Unrecoverable
A36: ProAdvisor certification (free, portable); all technical skills and process documentation; the MBA (untouched); the LLC shell (dormant free); client relationships (convert to employer, referral network, or an in-house role — a common outcome); WOSB certification (survives a pivot to any service line); the entire web/portal infrastructure (Brad reuses it) | C36: Sarah's time (opportunity cost ≈ the salary table above, the real cost); ~$2-6k marketing spend over 18 months; ~$1-2k/yr software; ~$1-1.4k/yr insurance; $0-400 legal
A37: Worst realistic case, stated plainly: the attempt costs roughly 18 months of forgone salary minus whatever the book sells for — and ends with Sarah more employable in the $72-145k band than she was at launch. That is the sense in which the attempt is "not a waste of time": every failure path terminates in a stronger resume, a sellable asset, or both.
A39: Source: Wind-down: Financial Cents/TaxDome termination-letter standards; The Tax Adviser retention guidance; multiples: Peak Business Valuation, Accounting Practice Sales; tuck-ins: CT Acquisitions + Inside Public Accounting deal reports; salaries: BLS OEWS May 2025 API + Robert Half 2026 (staffing-firm incentive flagged); posting volume: Indeed July 2026. Full citations Tab 14.

Sheet 13. Anticipated Questions
A1: ANTICIPATED QUESTIONS — THE HARD REVIEW
A2: An adversarial reviewer was asked to attack this plan. The 18 sharpest questions, with answers and the concessions adopted into the model.
A4: Capability & Capacity
A5: The question, as a skeptic asks it | B5: The answer | C5: Concession adopted
A6: "Your operator has an MBA and zero bookkeeping experience. ProAdvisor is a software exam you can pass in a weekend. Why should anyone trust you, and why believe your hours-per-client estimate?" | B6: Conceded in part: the certification is a tool credential, not competency proof, and this plan never presents it otherwise. The mitigation is structural: first books at reduced fee for warm-network businesses, CPA review purchased for the first year-end closes, and a skills runway (sandbox practice, a deliberately-wrecked file cleaned by checklist) before any stranger's books. | C6: Hours budgeted at 8-10/client for months 1-6; the 5-hour figure must be earned, not assumed
A7: "Sarah is the only person who can produce the product. What happens to the retainers if she is out six weeks?" | B7: The plan's largest operational risk, conceded. Mitigations: documented per-client close checklists from client #1 (which also enable hiring and sale), Brad cross-trained on mechanics, a backup-bookkeeper relationship built by month 6, and own-occupation disability insurance once revenue justifies it. | C7: Key-person risk carries a named tripwire in Tab 10
A8: "The plan says two people. It is really 1.0 production FTE, isn't it?" | B8: Yes. Brad's hours build systems, marketing, and pipeline; they do not close books. Stated in Tab 2 and every capacity number is computed on 1.0 production FTE. | C8: Adopted verbatim
A9: "Show me the real ceiling." | B9: Industry benchmarks put 10-20 full-service clients per bookkeeper, and a naive calculation (110 hours / 5 hrs per client) gives 22. The plan does not use that number, because it ignores the hours an owner-operator spends selling, learning, and running the firm. Tab 7 subtracts a 30% non-delivery reserve, leaving 77 deliverable hours and a computed ceiling of 15 mature clients, or about 8 while every client is still new. 15 is the number used everywhere in this plan; it is a live formula in Tab 7, so changing the reserve changes it. Quality breaks first in January-March, not in a typical month. | C9: One ceiling number, computed not asserted: 15. Hiring trigger at 12-14 clients, before the ceiling, not at it.
A11: Economics & Market
A12: Question | B12: Answer | C12: Concession adopted
A13: "Your LTV assumes retention you have not earned. What is it at realistic first-year retention?" | B13: At 70% retention LTV is ~$20k; at 85%, ~$40k; the industry-content $30k+ assumes established-firm retention. The model runs 75-85% for years 1-2 and treats 95% as a year-3 goal contingent on demonstrated quality. | C13: LTV restated to $15-20k planning figure (Tab 5)
A14: "Contractors and restaurants are among the most failure-prone client bases available. How does a client that dies in year two produce a five-year LTV?" | B14: It does not, and the blended model carries a client-mortality discount by segment. Restaurants (~49% five-year closure) are capped at ~25% of roster; the firm prefers 2yr+ businesses; professional services are the stable ballast. The niches are still right: high pain, high outsourcing willingness, low specialist competition. | C14: Roster caps and screening scorecard (Tabs 3-4)
A15: "Why does a contractor pay a rookie $450 when a national brand sells at $300?" | B15: The $300 tier keeps collapsing (Bench stranded thousands mid-year; Intuit is retiring QuickBooks Live itself, effective July 29, 2026). Local, named, responsive specialists price inside the umbrella the failures left standing. But conceded: early clients anchor low, which is why the first-ten pricing is $350-450 and mature pricing is earned through niche proof. | C15: The ramp is priced into every projection
A16: "Your cost structure leans on Intuit's 30% wholesale margin. Intuit has repriced ProAdvisor repeatedly. What happens when they do it again?" | B16: The margin is treated as a rebate, never as the profit line; billing is structured so software cost can pass through at retail if forced; Xero Level 1 is maintained as a credible exit. The core service margin survives the wholesale margin going to zero. | C16: Platform-risk tripwire in Tab 10
A17: "11-13k new DFW filings a month sounds impressive. New businesses are broke and die fast." | B17: Correct — it is a gross number and brand-new businesses are the industry's worst clients. The drip list is a cheap automated experiment whose value arrives at month 12+, when last year's filings have revenue, a shoebox, and their first tax-season panic. It ranks 5th of 6 channels. | C17: Expected conversion stated at under 1%
A18: "What does this firm do in a recession?" | B18: Resilient, not immune: 2009 CPA net fees were flat (+0.6%), 2020 compliance chaos actually raised demand. Offsetting dynamics: businesses cut in-house bookkeepers and outsource (tailwind for a $400-600 firm) while marginal clients die (headwind in these niches). The ~$190/mo cost base means the firm survives almost any revenue level — the true advantage over leveraged models. | C18: Churn-spike scenario in the risk register
A20: Tax & Household Structure
A21: Question | B21: Answer | C21: Concession adopted
A22: "Run the S-corp election math honestly — including the two-working-owner problem and QBI erosion, not the blog version." | B22: At $50k profit: reasonable compensation consumes everything; do not elect. At $100k: ~$4.2k gross FICA savings minus ~$2k admin minus $1.5-2.8k QBI erosion ≈ break-even; do not elect yet. At $150k+: net savings ~$3-4k/yr; worthwhile, marginally. Election earns its keep at sustained ~$150k+, clearly at $200k+. Bonus structural fact: as a community-property single-owner LLC, the entity stays a disregarded entity (no partnership return) until an election is ever made. | C22: Election deferred; revisit gate written at sustained $150k profit
A23: "Does QBI even apply? Bookkeeping is a specified service business." | B23: SSTB status is irrelevant below the thresholds: OBBBA (July 2025) made the 20% deduction permanent, and the 2026 MFJ phase-out does not begin until $403,500 of taxable income. This household is below it for years — the full 20% federal deduction on firm profits applies and is a genuine, quantifiable advantage of self-employment the plan claims explicitly. | C23: Claimed as a plan advantage, with the threshold cited
A24: "What does health insurance actually cost this household now that the enhanced ACA subsidies are dead?" | B24: The pivotal unpriced item, conceded and now priced. Brad: VA healthcare, stable. Sarah, best case: if Brad's rating is permanent-and-total, CHAMPVA covers her — no premium, $3,000 annual out-of-pocket cap — and the problem largely disappears. Otherwise: Texas 2026 benchmark premiums ~$661/mo pre-credit with the 400% FPL cliff back; budget $600-900/mo once household income crosses it, partly offset by the self-employed health-insurance deduction. | C24: ACTION ITEM: confirm P&T status in writing — it swings a five-figure annual line
A25: "Retirement?" | B25: A structural win: a solo 401k can cover both spouses — 2026 limits are $24,500 employee deferral each plus employer contributions to $72,000 total each, up to $144,000 combined capacity once profits allow. Chosen over SEP-IRA for higher effective limits at modest income plus Roth options. Note the interaction: an early S-corp election shrinks this capacity (distributions are not compensation), one more reason the election waits. | C25: Solo 401k named as the vehicle in the plan
A26: "Both spouses, one brand-new firm. Every planner calls this concentration risk." | B26: The household is not actually 100% concentrated: VA disability compensation is a fixed, inflation-adjusted, employment-independent floor most two-founder households lack. Sarah's employability is treated as a maintained asset (network and credentials kept warm, return-to-W-2 within a quarter). What the plan does not claim: that concentration is costless — hence disability insurance and the written kill criteria. | C26: The 9-12 month reserves rule (Tab 9)
A27: "Her market wage is real money. Why isn't this an expensive hobby?" | B27: On pure 2-3 year discounted cash, a corporate job likely wins — the plan does not pretend otherwise. The honest case: she was laid off (the comparison includes search time and market risk, not an offer in hand); the household's constraints favor flexibility a W-2 does not give; a firm at $15-20k MRR is sellable at ~1x collections, which a salary never is; QBI plus dual solo-401k capacity narrow the after-tax gap. The crossover is named: ~$15-20k MRR by month 30-36 beats the corporate path on money alone. Below that, the justification is autonomy and fit — stated out loud, not hidden. | C27: Crossover analysis embedded in Tabs 8 and 12
A29: Strategy & Certification
A30: Question | B30: Answer | C30: Concession adopted
A31: "Who actually closes the sale? Has Sarah ever done relationship sales? Does she want to?" | B31: Unvalidated, and the plan says so — it is the single least-tested assumption. The 90-day sprint (30 conversations, 10 proposals, 3 clients) tests it cheaply while the option remains to pivot to white-label production, which needs almost no selling at lower margin. | C31: Kill criteria in writing before launch
A32: "You plan to buy books of business. Sellers finance because transferred clients leave. Why would their clients stay with a firm this young?" | B32: They often would not, which is why acquisitions carry zero weight in the base case, wait until the firm's own retention is demonstrably above ~90% (month 24+ gate), and are structured seller-financed with retention earnouts and clawbacks — the market-standard protection that exists precisely because of this risk. | C32: Phase 2 only; zero weight in projections
A33: "What does WOSB actually get a two-person bookkeeping firm in 24 months?" | B33: Near-zero near-term revenue, stated plainly in Tab 11: WOSB set-asides in this NAICS were $1.1-1.5M/yr nationally and net-negative in FY25. It is filed because it is free, it is a credibility marker, and it is a long-term option — and the Texas HUB change (Dec 2025) is disclosed rather than discovered. | C33: Role wording throughout this plan is written to pass the SBA control test
A34: "Isn't AI going to eat this?" | B34: The 40-year evidence says automation shrinks employment while raising wages for the judgment layer that remains (employment -33%, real wages +40%, 1980-2018). This firm is built to own the judgment layer and automate its own mechanical layer. The residual risk — a good-enough autonomous product — has a named tripwire: if Intuit ships one with traction, the firm accelerates its move up the advisory ladder where the MBA lives anyway. | C34: Monitored threat with tripwire, not hand-waved
A36: Source: All figures in this tab trace to Tab 14 sources: S-corp/QBI math from 2026 parameters (SSA wage base $184,500; OBBBA §199A; SDO CPA admin-cost ranges; Dallas reasonable-comp benchmarks); CHAMPVA terms from VA guides; ACA from KFF + Texas Tribune; solo 401k from IRS limits via Fidelity/IRA Financial; recession data from CPA Trendlines (2009) and Intuit (2020).

Sheet 14. Sources
A1: SOURCES & METHODOLOGY
A2: Every load-bearing figure, graded. Verified = primary source retrieved directly. Directional = credible secondary. Anecdotal = labeled as such wherever used.
A4: Methodology
A5: Research was performed July 2026 by parallel investigation agents with source-quality grading. Government data was pulled directly from agency APIs (BLS, USAspending, SEC EDGAR) rather than from restatements. Content farms, affiliate/lead-gen education sites, and seller-conflicted sources (course sellers quoting their own value; credentialing bodies quoting uncontrolled surveys; staffing firms' incentives flagged) were identified and excluded or downweighted — the exclusion lists are auditable in the underlying research files. One original dataset was built for this plan: a 223-posting LinkedIn audit (114 full descriptions) testing which credentials employers actually name. Where evidence is anecdotal (practitioner forums), it is labeled anecdotal at point of use and never load-bearing alone.
A7: Primary / Government (Verified)
A8: Source | B8: Supports | C8: Grade | D8: Reference
A9: BLS OEWS May 2025 (via API) | B9: All wage data: DFW bookkeeper median $51,720; financial manager $169,200; TX/national percentiles | C9: Verified | D9: api.bls.gov series OEUN…43303113 et al.
A10: BLS Employment Projections 2024-34 + OOH | B10: Occupation -6% / -94,300 jobs; ~170,000 annual openings, 100% replacement; automation attribution | C10: Verified | D10: bls.gov/ooh (bookkeeping clerks)
A11: USAspending.gov API, NAICS 541219, FY2023-25 | B11: WOSB set-asides $1.1-1.5M/yr, net-negative FY25; SDVOSB $19-28M/yr (declined path) | C11: Verified (original pull) | D11: usaspending.gov API
A12: Intuit SEC Form 8-K, May 20, 2026 | B12: 17% workforce reduction, $300-340M charges, AI-native pivot | C12: Verified | D12: sec.gov EDGAR CIK 896878
A13: 13 CFR 127 & 128 (eCFR) | B13: WOSB ownership/control rules; community-property disregard; SDVOSB spouse-control provision (declined path) | C13: Verified | D13: ecfr.gov
A14: Texas Comptroller: Pub. 94-127 + 2025 data-processing rule; franchise/PIR; VetHUB pages | B14: Sales-tax treatment of services; compliance calendar; HUB→VetHUB restructuring | C14: Verified | D14: comptroller.texas.gov
A15: TSBPA enforcement guidance | B15: Non-CPAs may not use "accountant"/"accounting services" in public offers; no bookkeeping license exists in Texas | C15: Verified | D15: tsbpa.state.tx.us
A16: IRS: TFRP guidance; 1099 deadlines; Pub. 538; §199A/OBBBA parameters | B16: Personal liability for withheld taxes; Jan 31 deadline; cash-method eligibility; QBI 20% permanent, 2026 MFJ SSTB phase-out from $403,500 | C16: Verified | D16: irs.gov + Foster/Tax Foundation analyses
A17: SSA 2026 wage base ($184,500) | B17: S-corp election math | C17: Verified | D17: Thomson Reuters tax news
A18: Texas Tribune + Comptroller, Dec 2, 2025 | B18: Texas ended women/minority HUB; VetHUB veterans-only; litigation ongoing | C18: Verified | D18: texastribune.org
A19: Stanford GSB (Choi & Xie, 2025); NBER w33941 (Autor & Thompson, 2025) | B19: AI task-level effects (7.5-day faster closes); 1980-2018 employment -33% / real wages +40% | C19: Verified (academic) | D19: gsb.stanford.edu; nber.org/papers/w33941
A21: Industry & Benchmark (Verified-to-Directional)
A22: Source | B22: Supports | C22: Grade | D22: Reference
A23: AICPA: 2025 MAP Survey, 2024 CAS Benchmark (n=206), 2025 Trends | B23: Niche premium +51% revenue/client; graduates -6.6% YoY; CPA capacity shortage | C23: Verified | D23: aicpa.org
A24: Ignition 2025/26 Pricing Benchmark (n=219) | B24: Fixed-fee pricing bands; engagement-letter norms | C24: Verified | D24: ignitionapp.com
A25: Robert Half 2026 Salary Guide (Dallas) | B25: Full-charge $71,820-94,050; accounting manager $110-145k; asst controller $107-162k (staffing-firm incentive flagged; BLS medians run lower) | C25: Directional-strong | D25: roberthalf.com
A26: Peak Business Valuation; Accounting Practice Sales | B26: Practice multiples ~1.04-1.17x revenue / 2.55-3.32x SDE; write-up books 0.7-1.0x | C26: Directional-strong | D26: peakbusinessvaluation.com; accountingpracticesales.com
A27: KFF; Texas Tribune; healthinsurance.org (2026 ACA) | B27: TX premiums +35%; benchmark ~$661/mo; subsidy cliff returned | C27: Verified | D27: kff.org
A28: VA/CHAMPVA guides; Fidelity + IRA Financial (2026 solo 401k) | B28: CHAMPVA terms if P&T; $24,500/$72,000 2026 limits, spouse eligibility | C28: Verified | D28: va.gov; fidelity.com
A29: SmartFirm; Agiled (retention compilations) | B29: Small firms retain 60-70%; well-run 90-96% — basis for the honest 75-85% band | C29: Directional | D29: smartfirm.io; agiled.app
A30: Jetpack Workflow; ScribeOS | B30: Hours-per-client and clients-per-bookkeeper benchmarks | C30: Directional | D30: jetpackworkflow.com
A31: Owner.com; LendingTree (BLS-derived) | B31: Restaurant ~49% five-year closure; all-business 48.6% | C31: Directional-strong | D31: owner.com; lendingtree.com
A32: CPA Trendlines (2009); Intuit practitioner survey (2020) | B32: Recession behavior: fees flat, not down; compliance chaos raised demand | C32: Verified | D32: cpatrendlines.com
A33: Bench/Botkeeper collapse coverage; Intuit QuickBooks Live retirement | B33: Low-end structural failure; incumbent retreat | C33: Verified (multiple) | D33: court filings + trade press
A34: Texas SOS; SB 524 history (capitol.texas.gov) | B34: Veteran fee-waiver program lapsed Dec 2025; extension bill died in committee | C34: Verified | D34: capitol.texas.gov
A36: Original Data & Practitioner Sources (Anecdotal Labeled)
A37: Source | B37: Supports | C37: Grade | D37: Reference
A38: LinkedIn postings audit, July 2026 (built for this plan) | B38: 223 postings / 114 full descriptions: AIPB, NACPB, "Certified Bookkeeper" appear ZERO times; only ProAdvisor named (2%); QuickBooks 61%, Excel 54% of bookkeeper-titled roles | C38: Original data (single board, one point in time) | D38: Reproducible scripts archived
A39: Winnie Jayne (EA; ex-QuickBooks Live lead; 200+ cleanups) | B39: 12-step cleanup order; "procedural, not technical" failure mode; cleanup 3-5x time multiplier (directionally corroborated) | C39: Practitioner-strong | D39: winniejayne.com
A40: AccountingCoach (Averkamp, CPA); AccountingTools | B40: Adjusting entries; payroll journal entries; cash↔accrual conversion mechanics; COA sizing | C40: Reference-grade | D40: accountingcoach.com; accountingtools.com
A41: BudgetEase; Out of the Box Technology | B41: Undeposited Funds failure mode; COA five failure patterns | C41: Practitioner | D41: budgetease.biz
A42: Practitioner forums (r/Bookkeeping, r/Accounting, Intuit Community) | B42: 30-40 year veterans: "no one has ever asked for my credentials"; ProAdvisor-directory lead reports mixed; cleanup-is-hardest consensus; dissents reported in full | C42: Anecdotal (labeled; never load-bearing alone) | D42: Thread archives in research files
A43: DOJ press release (verified via Wayback) | B43: NACPB founder tax-evasion conviction — governance factor in skipping that credential | C43: Verified | D43: justice.gov archive
A45: Known Limitations
A46: (1) Hours-per-client is triangulated from benchmarks, not measured — the model prices the pessimistic end. (2) No rigorous survey of solo-firm revenue exists; the ceiling is derived from hours × rates. (3) Retention compilations are of uneven quality; the model uses the conservative band. (4) The VetHUB program's emergency-rule legal posture is unsettled (moot for the chosen path). (5) The LinkedIn audit is one board at one point in time; it bounds credential demand at low-single-digits, it does not prove zero. (6) 2026 ACA and tax parameters should be re-verified at each annual tax planning session with the CPA.
